CHANGES.txt
CONTRIBUTORS.txt
MANIFEST.in
README.txt
setup.cfg
setup.py
docs/HISTORY.txt
docs/INSTALL.txt
docs/LICENSE.GPL
docs/LICENSE.txt
valentine/__init__.py
valentine.contentportlets.egg-info/PKG-INFO
valentine.contentportlets.egg-info/SOURCES.txt
valentine.contentportlets.egg-info/dependency_links.txt
valentine.contentportlets.egg-info/entry_points.txt
valentine.contentportlets.egg-info/namespace_packages.txt
valentine.contentportlets.egg-info/not-zip-safe
valentine.contentportlets.egg-info/paster_plugins.txt
valentine.contentportlets.egg-info/requires.txt
valentine.contentportlets.egg-info/top_level.txt
valentine/contentportlets/README.txt
valentine/contentportlets/__init__.py
valentine/contentportlets/config.py
valentine/contentportlets/configure.zcml
valentine/contentportlets/doceststofix.txt
valentine/contentportlets/interfaces.py
valentine/contentportlets/browser/__init__.py
valentine/contentportlets/browser/configure.zcml
valentine/contentportlets/browser/contentportlets.py
valentine/contentportlets/browser/templates/managecontentportlets.pt
valentine/contentportlets/manager/__init__.py
valentine/contentportlets/manager/configure.zcml
valentine/contentportlets/manager/manager.py
valentine/contentportlets/manager/portlets.pt
valentine/contentportlets/profiles/default/browserlayer.xml
valentine/contentportlets/profiles/default/metadata.xml
valentine/contentportlets/profiles/default/portlets.xml
valentine/contentportlets/tests/__init__.py
valentine/contentportlets/tests/base.py
valentine/contentportlets/tests/test_doctest.py