Metadata-Version: 1.0
Name: valentine.contentportlets
Version: 0.1
Summary: UNKNOWN
Home-page: http://dev.plone.org/collective/browser/valentine.contentportlets/trunk
Author: Sasha Vincic
Author-email: sasha dot vincic at valentinwebsystems dot com
License: GPL
Keywords: plone
Platform: UNKNOWN
Classifier: Framework :: Plone
Classifier: Intended Audience :: Developers
Classifier: License :: OSI Approved :: GNU General Public License (GPL)
